AUTHOR
LICENSE
MANIFEST.in
README.rst
setup.cfg
setup.py
doc/source/conf.py
doc/source/index.rst
doc/source/_static/pysphinxdoc.png
doc/source/_static/carousel/image1.png
doc/source/_static/carousel/image2.png
doc/source/_static/carousel/image3.png
doc/source/generated/documentation.rst
doc/source/generated/installation.rst
doc/source/generated/pysphinxdoc.docgen.rst
doc/source/generated/pysphinxdoc.rst
doc/source/generated/_templates/layout.html
pysphinxdoc/__init__.py
pysphinxdoc/docgen.py
pysphinxdoc/info.py
pysphinxdoc/sphinxdoc
pysphinxdoc.egg-info/PKG-INFO
pysphinxdoc.egg-info/SOURCES.txt
pysphinxdoc.egg-info/dependency_links.txt
pysphinxdoc.egg-info/requires.txt
pysphinxdoc.egg-info/top_level.txt
pysphinxdoc/resources/Makefile
pysphinxdoc/resources/conf.py
pysphinxdoc/resources/index.rst
pysphinxdoc/resources/installation.rst
pysphinxdoc/resources/layout.html
pysphinxdoc/sphinxext/custom_ext/__init__.py
pysphinxdoc/sphinxext/custom_ext/hidden_code_block.py
pysphinxdoc/sphinxext/custom_ext/hidden_technical_block.py
pysphinxdoc/sphinxext/custom_ext/link_to_block.py
pysphinxdoc/sphinxext/numpy_ext/LICENSE.txt
pysphinxdoc/sphinxext/numpy_ext/__init__.py
pysphinxdoc/sphinxext/numpy_ext/comment_eater.py
pysphinxdoc/sphinxext/numpy_ext/compiler_unparse.py
pysphinxdoc/sphinxext/numpy_ext/docscrape.py
pysphinxdoc/sphinxext/numpy_ext/docscrape_sphinx.py
pysphinxdoc/sphinxext/numpy_ext/linkcode.py
pysphinxdoc/sphinxext/numpy_ext/numpydoc.py
pysphinxdoc/sphinxext/numpy_ext/phantom_import.py
pysphinxdoc/sphinxext/numpy_ext/plot_directive.py
pysphinxdoc/sphinxext/numpy_ext/traitsdoc.py
pysphinxdoc/templates/class.rst
pysphinxdoc/templates/function.rst
pysphinxdoc/themes/scikit-learn/theme.conf
pysphinxdoc/themes/scikit-learn/static/ML_MAPS_README.rst
pysphinxdoc/themes/scikit-learn/static/go.gif
pysphinxdoc/themes/scikit-learn/static/jquery.js
pysphinxdoc/themes/scikit-learn/static/nature.css
pysphinxdoc/themes/scikit-learn/static/sidebar.js
pysphinxdoc/themes/scikit-learn/static/css/bootstrap.css
pysphinxdoc/themes/scikit-learn/static/css/bootstrap.min.css
pysphinxdoc/themes/scikit-learn/static/img/glyphicons-halflings-white.png
