Metadata-Version: 1.1
Name: pysphinxdoc
Version: 1.0.0
Summary: [pysphinxdoc] API Documentation Generation Tool.
Home-page: https://github.com/AGrigis/pysphinxdoc
Author: pysphinxdoc developers
Author-email: antoine.grigis@cea.fr
License: CeCILL-B
Platform: OS Independent
Classifier: Development Status :: 5 - Production/Stable
Classifier: Environment :: Console
Classifier: Environment :: X11 Applications :: Qt
Classifier: Operating System :: OS Independent
Classifier: Programming Language :: Python
Classifier: Topic :: Scientific/Engineering
Classifier: Topic :: Utilities
